servo/__init__.py
servo/__main__.py
micropython_servo-1.0.0.dist-info/LICENSE
micropython_servo-1.0.0.dist-info/METADATA
micropython_servo-1.0.0.dist-info/WHEEL
micropython_servo-1.0.0.dist-info/top_level.txt
micropython_servo-1.0.0.dist-info/RECORD
