Metadata-Version: 2.1
Name: micropython-servo
Version: 1.0.0
Summary: Use rc servos with PWM in micropython in a tidy way
Author-email: redoxcode <redoxcode@github.com>
License: MIT License
Project-URL: Homepage, https://github.com/redoxcode/micropython-servo
Keywords: servo,PWM
Classifier: License :: OSI Approved :: MIT License
Classifier: Programming Language :: Python :: Implementation :: MicroPython
License-File: LICENSE
Provides-Extra: dev
